tfmindi/__init__.py
tfmindi/datasets.py
tfmindi/io.py
tfmindi/merge.py
tfmindi/types.py
tfmindi/backends/__init__.py
tfmindi/pl/__init__.py
tfmindi/pl/_utils.py
tfmindi/pl/contributions.py
tfmindi/pl/dbd_heatmap.py
tfmindi/pl/logo.py
tfmindi/pl/region_topics.py
tfmindi/pl/tsne.py
tfmindi/pp/__init__.py
tfmindi/pp/mappings.py
tfmindi/pp/seqlets.py
tfmindi/tl/__init__.py
tfmindi/tl/cluster.py
tfmindi/tl/patterns.py
tfmindi/tl/topic_modeling.py
tfmindi-1.2.0.dist-info/METADATA
tfmindi-1.2.0.dist-info/WHEEL
tfmindi-1.2.0.dist-info/licenses/LICENSE
tfmindi-1.2.0.dist-info/RECORD
