Metadata-Version: 2.4
Name: tfmindi
Version: 1.2.0
Summary: TF-MInDi: Transcription Factor Motifs and Instances Discovery
Project-URL: Documentation, https://tfmindi.readthedocs.io/
Project-URL: Homepage, https://github.com/aertslab/TF-MInDi
Project-URL: Source, https://github.com/aertslab/TF-MInDi
Author: Seppe De Winter
Maintainer-email: Seppe De Winter <seppe.dewinter@kuleuven.be>, Lukas Mahieu <lukas.mahieu@kuleuven.be>
License: 
License-File: LICENSE
Classifier: Programming Language :: Python :: 3 :: Only
Classifier: Programming Language :: Python :: 3.10
Classifier: Programming Language :: Python :: 3.11
Classifier: Programming Language :: Python :: 3.12
Requires-Python: <3.13,>=3.10.2
Requires-Dist: anndata
Requires-Dist: h5py>=3.14
Requires-Dist: igraph
Requires-Dist: itaxotools-mafftpy>=0.3
Requires-Dist: lda
Requires-Dist: logomaker
Requires-Dist: matplotlib
Requires-Dist: memelite
Requires-Dist: numba
Requires-Dist: numpy
Requires-Dist: pandas
Requires-Dist: pooch
Requires-Dist: pybigwig
Requires-Dist: scanpy
Requires-Dist: scipy
Requires-Dist: seaborn
Requires-Dist: session-info2
Provides-Extra: dev
Requires-Dist: pre-commit; extra == 'dev'
Requires-Dist: twine>=4.0.2; extra == 'dev'
Provides-Extra: doc
Requires-Dist: docutils!=0.18.*,!=0.19.*,>=0.8; extra == 'doc'
Requires-Dist: ipykernel; extra == 'doc'
Requires-Dist: ipython; extra == 'doc'
Requires-Dist: myst-nb>=1.1; extra == 'doc'
Requires-Dist: pandas; extra == 'doc'
Requires-Dist: setuptools; extra == 'doc'
Requires-Dist: sphinx-autodoc-typehints; extra == 'doc'
Requires-Dist: sphinx-book-theme>=1; extra == 'doc'
Requires-Dist: sphinx-copybutton; extra == 'doc'
Requires-Dist: sphinx-tabs>=3.4.7; extra == 'doc'
Requires-Dist: sphinx<9,>=8.1; extra == 'doc'
Requires-Dist: sphinxcontrib-bibtex>=1; extra == 'doc'
Requires-Dist: sphinxext-opengraph; extra == 'doc'
Provides-Extra: gpu
Requires-Dist: cudf-cu12==25.8.*; extra == 'gpu'
Requires-Dist: cugraph-cu12==25.8.*; extra == 'gpu'
Requires-Dist: cuml-cu12==25.8.*; extra == 'gpu'
Requires-Dist: cupy-cuda12x; extra == 'gpu'
Requires-Dist: rapids-singlecell; extra == 'gpu'
Provides-Extra: test
Requires-Dist: coverage; extra == 'test'
Requires-Dist: pytest; extra == 'test'
